fastapi_cloud_healthcheck/__init__.py
fastapi_cloud_healthcheck/api/routes.py
fastapi_cloud_healthcheck/core/enums.py
fastapi_cloud_healthcheck/core/interface.py
fastapi_cloud_healthcheck/core/models.py
fastapi_cloud_healthcheck/services/base.py
fastapi_cloud_healthcheck/services/factory.py
fastapi_cloud_healthcheck-0.1.5.dist-info/LICENSE
fastapi_cloud_healthcheck-0.1.5.dist-info/METADATA
fastapi_cloud_healthcheck-0.1.5.dist-info/WHEEL
fastapi_cloud_healthcheck-0.1.5.dist-info/RECORD
