Metadata-Version: 2.1
Name: fastapi-cloud-healthcheck
Version: 0.1.5
Summary: This package provides a flexible and modular health check framework tailored for cloud services such as AWS and Azure, leveraging FastAPI for efficient routing and response handling.
Home-page: https://github.com/yogeshselvarajan/fastapi_cloud_healthcheck
License: MIT
Keywords: fastapi,healthcheck,cloud,boto3,azure-sdk,aws,azure
Author: Yogesh Selvarajan
Author-email: yogeshselvarajan@gmail.com
Requires-Python: >=3.5,<4.0
Classifier: Framework :: FastAPI
Classifier: License :: OSI Approved :: MIT License
Classifier: Operating System :: OS Independent
Classifier: Programming Language :: Python :: 3
Classifier: Programming Language :: Python :: 3.5
Classifier: Programming Language :: Python :: 3.6
Classifier: Programming Language :: Python :: 3.7
Classifier: Programming Language :: Python :: 3.8
Classifier: Programming Language :: Python :: 3.9
Classifier: Programming Language :: Python :: 3.10
Classifier: Programming Language :: Python :: 3.11
Classifier: Programming Language :: Python :: 3.12
Requires-Dist: fastapi (>=0.115.0,<0.116.0)
Requires-Dist: pydantic (>=2.9.2,<3.0.0)
Project-URL: Repository, https://github.com/yogeshselvarajan/fastapi_cloud_healthcheck
